arcAGI2024/__init__.py
arcAGI2024/base.py
arcAGI2024/decoder.py
arcAGI2024/grad_utils.py
arcAGI2024/logging.py
arcAGI2024/losses.py
arcAGI2024/model.py
arcAGI2024/pretraining.py
arcAGI2024/sampling.py
arcAGI2024/vocabulary.py
arcAGI2024/data/__init__.py
arcAGI2024/data/base.py
arcAGI2024/data/pretraining.py
arcAGI2024/memory/__init__.py
arcAGI2024/memory/deep_memory.py
arcAGI2024/memory/fast_memory.py
arcAGI2024-0.4.6.dist-info/LICENSE
arcAGI2024-0.4.6.dist-info/METADATA
arcAGI2024-0.4.6.dist-info/WHEEL
arcAGI2024-0.4.6.dist-info/top_level.txt
arcAGI2024-0.4.6.dist-info/RECORD
