Metadata-Version: 2.1
Name: arcAGI2024
Version: 0.4.6
Summary: Support mechanism for the arc agi project
Author: Chris
Author-email: your.email@example.com
Requires-Python: >=3.10
License-File: LICENSE
Requires-Dist: torch
Requires-Dist: tokenizers
Requires-Dist: transformers
Requires-Dist: typeguard
Requires-Dist: tqdm
Requires-Dist: numpy
Requires-Dist: pandas
